spaik_sdk/__init__.py
spaik_sdk/py.typed
spaik_sdk/agent/__init__.py
spaik_sdk/agent/base_agent.py
spaik_sdk/attachments/__init__.py
spaik_sdk/attachments/builder.py
spaik_sdk/attachments/file_storage_provider.py
spaik_sdk/attachments/mime_types.py
spaik_sdk/attachments/models.py
spaik_sdk/attachments/provider_support.py
spaik_sdk/attachments/storage/__init__.py
spaik_sdk/attachments/storage/base_file_storage.py
spaik_sdk/attachments/storage/impl/__init__.py
spaik_sdk/attachments/storage/impl/local_file_storage.py
spaik_sdk/audio/__init__.py
spaik_sdk/audio/options.py
spaik_sdk/audio/stt.py
spaik_sdk/audio/tts.py
spaik_sdk/audio/providers/__init__.py
spaik_sdk/audio/providers/google_tts.py
spaik_sdk/audio/providers/openai_stt.py
spaik_sdk/audio/providers/openai_tts.py
spaik_sdk/config/credentials_provider.py
spaik_sdk/config/env.py
spaik_sdk/config/env_credentials_provider.py
spaik_sdk/config/get_credentials_provider.py
spaik_sdk/image_gen/__init__.py
spaik_sdk/image_gen/image_generator.py
spaik_sdk/image_gen/options.py
spaik_sdk/image_gen/providers/__init__.py
spaik_sdk/image_gen/providers/google.py
spaik_sdk/image_gen/providers/openai.py
spaik_sdk/llm/__init__.py
spaik_sdk/llm/cancellation_handle.py
spaik_sdk/llm/converters.py
spaik_sdk/llm/extract_error_message.py
spaik_sdk/llm/langchain_loop_manager.py
spaik_sdk/llm/langchain_service.py
spaik_sdk/llm/message_handler.py
spaik_sdk/llm/consumption/__init__.py
spaik_sdk/llm/consumption/consumption_estimate.py
spaik_sdk/llm/consumption/consumption_estimate_builder.py
spaik_sdk/llm/consumption/consumption_extractor.py
spaik_sdk/llm/consumption/token_usage.py
spaik_sdk/llm/cost/__init__.py
spaik_sdk/llm/cost/builtin_cost_provider.py
spaik_sdk/llm/cost/cost_estimate.py
spaik_sdk/llm/cost/cost_provider.py
spaik_sdk/llm/streaming/__init__.py
spaik_sdk/llm/streaming/block_manager.py
spaik_sdk/llm/streaming/models.py
spaik_sdk/llm/streaming/streaming_content_handler.py
spaik_sdk/llm/streaming/streaming_event_handler.py
spaik_sdk-0.6.5.dist-info/METADATA
spaik_sdk-0.6.5.dist-info/WHEEL
spaik_sdk-0.6.5.dist-info/RECORD
