Metadata-Version: 2.4
Name: spaik-sdk
Version: 0.6.5
Summary: Python SDK for building AI agents with multi-LLM support, streaming, and production-ready infrastructure
Project-URL: Homepage, https://github.com/siilisolutions/spaik-sdk
Project-URL: Repository, https://github.com/siilisolutions/spaik-sdk
Project-URL: Documentation, https://github.com/siilisolutions/spaik-sdk#readme
Author-email: Siili Solutions Oyj <info@siili.com>
License-Expression: MIT
Keywords: agents,ai,anthropic,claude,gpt,langchain,llm,openai,streaming
Classifier: Development Status :: 4 - Beta
Classifier: Intended Audience :: Developers
Classifier: License :: OSI Approved :: MIT License
Classifier: Programming Language :: Python :: 3
Classifier: Programming Language :: Python :: 3.10
Classifier: Programming Language :: Python :: 3.11
Classifier: Programming Language :: Python :: 3.12
Classifier: Topic :: Scientific/Engineering :: Artificial Intelligence
Requires-Python: >=3.10
Requires-Dist: aioconsole>=0.8.1
Requires-Dist: azure-storage-blob
Requires-Dist: cryptography>=41.0.0
Requires-Dist: dotenv>=0.9.9
Requires-Dist: fastapi>=0.115.12
Requires-Dist: httpx>=0.25.0
Requires-Dist: langchain-anthropic>=1.3.0
Requires-Dist: langchain-core>=1.2.0
Requires-Dist: langchain-google-genai>=4.0.0
Requires-Dist: langchain-mcp-adapters>=0.2.1
Requires-Dist: langchain-ollama>=0.3.0
Requires-Dist: langchain-openai>=1.1.0
Requires-Dist: langchain-tavily>=0.2.15
Requires-Dist: langchain>=1.2.0
Requires-Dist: langgraph>=1.0.0
Requires-Dist: mcp>=1.9.2
Requires-Dist: pandas-stubs
Requires-Dist: pandas>=2.0.3
Requires-Dist: pyjwt>=2.8.0
Requires-Dist: pytest-asyncio>=0.21.1
Requires-Dist: pytest-cov>=4.1.0
Requires-Dist: pytest-mock>=3.11.1
Requires-Dist: pytest>=7.4.0
Requires-Dist: requests>=2.31.0
Requires-Dist: restrictedpython>=8.0
Requires-Dist: rich>=14.0.0
Requires-Dist: uvicorn>=0.33.0
Provides-Extra: dev
Requires-Dist: black; extra == 'dev'
Requires-Dist: mypy; extra == 'dev'
Requires-Dist: ruff; extra == 'dev'
